seven_deadly_swarms/__init__.py
seven_deadly_swarms/swarms.py
seven_deadly_swarms-1.0.1.dist-info/LICENSE
seven_deadly_swarms-1.0.1.dist-info/METADATA
seven_deadly_swarms-1.0.1.dist-info/WHEEL
seven_deadly_swarms-1.0.1.dist-info/top_level.txt
seven_deadly_swarms-1.0.1.dist-info/RECORD
