Metadata-Version: 2.1
Name: seven_deadly_swarms
Version: 1.0.1
Summary: A Python library to modify text based on the seven deadly sins.
Home-page: https://github.com/scottleedavis/seven_deadly_swarms
Author: Scott Davis
Author-email: scottleedavis@gmail.com
Classifier: Programming Language :: Python :: 3
Classifier: License :: OSI Approved :: MIT License
License-File: LICENSE
Requires-Dist: openai>=0.27.0
